radixtarget-4.2.0.dist-info/METADATA
radixtarget-4.2.0.dist-info/WHEEL
radixtarget-4.2.0.dist-info/licenses/LICENSE
radixtarget.libs/libgcc_s-6d2d9dc8.so.1
radixtarget/__init__.py
radixtarget/_radixtarget.cpython-313-x86_64-linux-musl.so
radixtarget/radixtarget.py
radixtarget/test/__init__.py
radixtarget/test/cidrs.txt
radixtarget/test/test_rust_radixtarget.py
radixtarget/tree/base.py
radixtarget/tree/dns.py
radixtarget/tree/ip.py
radixtarget-4.2.0.dist-info/RECORD
