Metadata-Version: 2.4
Name: radixtarget
Version: 4.2.0
Classifier: Development Status :: 4 - Beta
Classifier: Intended Audience :: Developers
Classifier: License :: OSI Approved :: GNU General Public License v3 (GPLv3)
Classifier: Programming Language :: Python :: 3
Classifier: Programming Language :: Python :: 3.9
Classifier: Programming Language :: Python :: 3.10
Classifier: Programming Language :: Python :: 3.11
Classifier: Programming Language :: Python :: 3.12
Classifier: Programming Language :: Python :: 3.13
Classifier: Programming Language :: Python :: 3.14
Classifier: Programming Language :: Rust
Classifier: Topic :: Software Development :: Libraries
Classifier: Topic :: System :: Networking
License-File: LICENSE
Summary: Fast radix tree for IP addresses and DNS names
Keywords: radix,tree,ip,dns,networking
Author: TheTechromancer
License: GPL-3.0
Requires-Python: >=3.9
Project-URL: Homepage, https://github.com/blacklanternsecurity/radixtarget
Project-URL: Repository, https://github.com/blacklanternsecurity/radixtarget
Project-URL: Bug Tracker, https://github.com/blacklanternsecurity/radixtarget/issues
